{
  "name": "Studio Voxel 3D — Admin",
  "short_name": "Voxel Admin",
  "description": "Painel administrativo Studio Voxel 3D Consignação",
  "start_url": "/studiovoxel3d/admin.html",
  "scope": "/studiovoxel3d/",
  "display": "standalone",
  "background_color": "#080808",
  "theme_color": "#080808",
  "orientation": "portrait",
  "icons": [
    {
      "src": "icon-192.png",
      "sizes": "192x192",
      "type": "image/png",
      "purpose": "any maskable"
    },
    {
      "src": "icon-512.png",
      "sizes": "512x512",
      "type": "image/png",
      "purpose": "any maskable"
    }
  ]
}